aiohubot/__init__.py
aiohubot/__main__.py
aiohubot/core.py
aiohubot/plugins.py
aiohubot/robot.py
aiohubot/adapters/__init__.py
aiohubot/adapters/shell.py
aiohubot/datastores/__init__.py
aiohubot/datastores/memory.py
aiohubot-0.4.7.dist-info/LICENSE
aiohubot-0.4.7.dist-info/METADATA
aiohubot-0.4.7.dist-info/WHEEL
aiohubot-0.4.7.dist-info/top_level.txt
aiohubot-0.4.7.dist-info/RECORD
