Metadata-Version: 2.1
Name: aiohubot
Version: 0.4.7
Summary: UNKNOWN
Home-page: https://github.com/LFLab/aiohubot
Author: Lanfon
Author-email: lanfon72@gmail.com
License: UNKNOWN
Platform: UNKNOWN
Classifier: Development Status :: 3 - Alpha
Classifier: Intended Audience :: Developers
Classifier: License :: OSI Approved :: MIT License
Classifier: Operating System :: OS Independent
Classifier: Programming Language :: Python :: 3.6
Classifier: Programming Language :: Python :: 3.7
Requires-Python: >=3.6
Requires-Dist: pyee (<7,>=6.*)
Requires-Dist: aiohttp (<4,>=3.*)
Provides-Extra: http_auth
Requires-Dist: aiohttp-basicauth ; extra == 'http_auth'
